{
  "AltLookAngle": {
    "x": 0,
    "y": 0,
    "z": 0
  },
  "Autoraise": true,
  "ColorDiffuse": {
    "b": 0.71324,
    "g": 0.71324,
    "r": 0.71324
  },
  "ContainedObjects_order": [
    "B2BattleDroid.a8f97f",
    "B2BattleDroid.73fabe",
    "B2BattleDroid.1ad9b7",
    "NuteGunray.abe644",
    "STAP.512775",
    "STAP.98bfb9",
    "VultureDroid.ac5ee1",
    "VultureDroid.8f92a4",
    "VultureDroid.604443",
    "Droideka.b69523",
    "Droideka.990941",
    "Tri-Fighter.faef31",
    "Tri-Fighter.13f4b4",
    "WatTambor.8d5301",
    "Magnaguard.98287b",
    "Magnaguard.d9be61",
    "MTT.648530",
    "MTT.a963ea",
    "AAT.90bbdc",
    "AdmiralTrench.421c52",
    "GeneralGrievous.4b3f93",
    "AsajjVentress.6bd9bd",
    "CountDooku.8d098e"
  ],
  "ContainedObjects_path": "SeparatistGalaxyDeck.fe508a",
  "CustomDeck": {
    "68": {
      "BackIsHidden": true,
      "BackURL": "https://steamusercontent-a.akamaihd.net/ugc/2020465330532070569/ABD27CB67122C80E4B40DF419BEBEDFB60702FC3/",
      "FaceURL": "https://steamusercontent-a.akamaihd.net/ugc/2394314828581900843/A3A99B20AB2360F38531375EF80B5092A59FFEFB/",
      "NumHeight": 4,
      "NumWidth": 6,
      "Type": 0,
      "UniqueBack": false
    }
  },
  "DeckIDs": [
    6800,
    6802,
    6801,
    6803,
    6805,
    6804,
    6822,
    6821,
    6820,
    6806,
    6807,
    6808,
    6809,
    6810,
    6812,
    6811,
    6813,
    6814,
    6815,
    6816,
    6817,
    6818,
    6819
  ],
  "Description": "",
  "DragSelectable": true,
  "GMNotes": "",
  "GUID": "fe508a",
  "Grid": true,
  "GridProjection": false,
  "Hands": false,
  "HideWhenFaceDown": true,
  "IgnoreFoW": false,
  "LayoutGroupSortIndex": 0,
  "Locked": true,
  "LuaScript": "",
  "LuaScriptState": "",
  "MeasureMovement": false,
  "Name": "Deck",
  "Nickname": "Separatist Galaxy Deck",
  "SidewaysCard": false,
  "Snap": true,
  "Sticky": true,
  "Tags": [
    "separatist",
    "unit"
  ],
  "Tooltip": true,
  "Transform": {
    "posX": -2.996,
    "posY": 0.272,
    "posZ": -12.503,
    "rotX": 0,
    "rotY": 180,
    "rotZ": 0,
    "scaleX": 2.1,
    "scaleY": 1,
    "scaleZ": 2.1
  },
  "Value": 0,
  "XmlUI": ""
}
